  {"position": 1, "domain_name": "veesp.com", "date": "2026-01-24"}
  {"position": 2, "domain_name": "apple.com", "date": "2026-01-24"}
  {"position": 3, "domain_name": "fbcdn.net", "date": "2026-01-24"}
  {"position": 4, "domain_name": "azure.com", "date": "2026-01-24"}
  {"position": 5, "domain_name": "gstatic.com", "date": "2026-01-24"}
  {"position": 6, "domain_name": "aaplimg.com", "date": "2026-01-24"}
  {"position": 7, "domain_name": "office.net", "date": "2026-01-24"}
  {"position": 8, "domain_name": "cnfracs.com", "date": "2026-01-24"}
  {"position": 9, "domain_name": "aws.dev", "date": "2026-01-24"}
  {"position": 10, "domain_name": "ranchwifi.com", "date": "2026-01-24"}
  {"position": 11, "domain_name": "apple-dns.net", "date": "2026-01-24"}
  {"position": 12, "domain_name": "ys7.com", "date": "2026-01-24"}
  {"position": 13, "domain_name": "cloudflare-dns.com", "date": "2026-01-24"}
  {"position": 14, "domain_name": "microsoftonline.com", "date": "2026-01-24"}
  {"position": 15, "domain_name": "msn.com", "date": "2026-01-24"}
  {"position": 16, "domain_name": "ui.com", "date": "2026-01-24"}
  {"position": 17, "domain_name": "live.com", "date": "2026-01-24"}
  {"position": 18, "domain_name": "bing.com", "date": "2026-01-24"}
  {"position": 19, "domain_name": "samsungcloudsolution.com", "date": "2026-01-24"}
  {"position": 20, "domain_name": "tiktokv.com", "date": "2026-01-24"}
  {"position": 21, "domain_name": "mtgglobals.com", "date": "2026-01-24"}
  {"position": 22, "domain_name": "youtube.com", "date": "2026-01-24"}
  {"position": 23, "domain_name": "yourdomainprovider.net", "date": "2026-01-24"}
  {"position": 24, "domain_name": "linkedin.com", "date": "2026-01-24"}
  {"position": 25, "domain_name": "gmail.com", "date": "2026-01-24"}
  {"position": 26, "domain_name": "wikipedia.org", "date": "2026-01-24"}
  {"position": 27, "domain_name": "webex.com", "date": "2026-01-24"}
  {"position": 28, "domain_name": "online-metrix.net", "date": "2026-01-24"}
  {"position": 29, "domain_name": "trafficmanager.net", "date": "2026-01-24"}
  {"position": 30, "domain_name": "samsungcloudsolution.net", "date": "2026-01-24"}
  {"position": 31, "domain_name": "adtrafficquality.google", "date": "2026-01-24"}
  {"position": 32, "domain_name": "ojsbdjn.com", "date": "2026-01-24"}
  {"position": 33, "domain_name": "amazon-adsystem.com", "date": "2026-01-24"}
  {"position": 34, "domain_name": "gvt1.com", "date": "2026-01-24"}
  {"position": 35, "domain_name": "ytimg.com", "date": "2026-01-24"}
  {"position": 36, "domain_name": "edge.apple", "date": "2026-01-24"}
  {"position": 37, "domain_name": "netflix.com", "date": "2026-01-24"}
  {"position": 38, "domain_name": "app-analytics-services.com", "date": "2026-01-24"}
  {"position": 39, "domain_name": "capitec.com", "date": "2026-01-24"}
  {"position": 40, "domain_name": "apdcdn.com", "date": "2026-01-24"}
  {"position": 41, "domain_name": "obihai.com", "date": "2026-01-24"}
  {"position": 42, "domain_name": "kaspersky.com", "date": "2026-01-24"}
  {"position": 43, "domain_name": "twimg.com", "date": "2026-01-24"}
  {"position": 44, "domain_name": "docker.io", "date": "2026-01-24"}
  {"position": 45, "domain_name": "eset.com", "date": "2026-01-24"}
  {"position": 46, "domain_name": "trademe.co.nz", "date": "2026-01-24"}
  {"position": 47, "domain_name": "conviva.com", "date": "2026-01-24"}
  {"position": 48, "domain_name": "google.com", "date": "2026-01-24"}
  {"position": 49, "domain_name": "bidswitch.net", "date": "2026-01-24"}
  {"position": 50, "domain_name": "discord.com", "date": "2026-01-24"}
  {"position": 51, "domain_name": "dzen.ru", "date": "2026-01-24"}
  {"position": 52, "domain_name": "catonet.works", "date": "2026-01-24"}
  {"position": 53, "domain_name": "miwifi.com", "date": "2026-01-24"}
  {"position": 54, "domain_name": "epicgames.com", "date": "2026-01-24"}
  {"position": 55, "domain_name": "tiktokcdn-eu.com", "date": "2026-01-24"}
  {"position": 56, "domain_name": "digicert.com", "date": "2026-01-24"}
  {"position": 57, "domain_name": "chick-fil-a.com", "date": "2026-01-24"}
  {"position": 58, "domain_name": "omniroot.com", "date": "2026-01-24"}
  {"position": 59, "domain_name": "proton.me", "date": "2026-01-24"}
  {"position": 60, "domain_name": "rustdesk.com", "date": "2026-01-24"}
  {"position": 61, "domain_name": "byte008.com", "date": "2026-01-24"}
  {"position": 62, "domain_name": "verisign.com", "date": "2026-01-24"}
  {"position": 63, "domain_name": "cloudappsecurity.com", "date": "2026-01-24"}
  {"position": 64, "domain_name": "sway.com", "date": "2026-01-24"}
  {"position": 65, "domain_name": "ggpht.com", "date": "2026-01-24"}
  {"position": 66, "domain_name": "360yield.com", "date": "2026-01-24"}
  {"position": 67, "domain_name": "getcontact.com", "date": "2026-01-24"}
  {"position": 68, "domain_name": "vidaahub.com", "date": "2026-01-24"}
  {"position": 69, "domain_name": "office365.com", "date": "2026-01-24"}
  {"position": 70, "domain_name": "dropbox.com", "date": "2026-01-24"}
  {"position": 71, "domain_name": "easebar.com", "date": "2026-01-24"}
  {"position": 72, "domain_name": "speedsmart.net", "date": "2026-01-24"}
  {"position": 73, "domain_name": "x96.us", "date": "2026-01-24"}
  {"position": 74, "domain_name": "xiaomi.com", "date": "2026-01-24"}
  {"position": 75, "domain_name": "no-ip.com", "date": "2026-01-24"}
  {"position": 76, "domain_name": "bugsnag.com", "date": "2026-01-24"}
  {"position": 77, "domain_name": "aniview.com", "date": "2026-01-24"}
  {"position": 78, "domain_name": "bqnmxkyse.com", "date": "2026-01-24"}
  {"position": 79, "domain_name": "cmliussss.net", "date": "2026-01-24"}
  {"position": 80, "domain_name": "t-msedge.net", "date": "2026-01-24"}
  {"position": 81, "domain_name": "wbx2.com", "date": "2026-01-24"}
  {"position": 82, "domain_name": "pv-cdn.net", "date": "2026-01-24"}
  {"position": 83, "domain_name": "lgeapi.com", "date": "2026-01-24"}
  {"position": 84, "domain_name": "ovh.net", "date": "2026-01-24"}
  {"position": 85, "domain_name": "phncdn.com", "date": "2026-01-24"}
  {"position": 86, "domain_name": "lool.bz", "date": "2026-01-24"}
  {"position": 87, "domain_name": "teridioncloud.net", "date": "2026-01-24"}
  {"position": 88, "domain_name": "optimizely.com", "date": "2026-01-24"}
  {"position": 89, "domain_name": "trxdnscloud.ru", "date": "2026-01-24"}
  {"position": 90, "domain_name": "ggblueshark.com", "date": "2026-01-24"}
  {"position": 91, "domain_name": "sc-gw.com", "date": "2026-01-24"}
  {"position": 92, "domain_name": "mozilla.com", "date": "2026-01-24"}
  {"position": 93, "domain_name": "imsvg.com", "date": "2026-01-24"}
  {"position": 94, "domain_name": "meraki.com", "date": "2026-01-24"}
  {"position": 95, "domain_name": "nubway.com", "date": "2026-01-24"}
  {"position": 96, "domain_name": "ttdns2.com", "date": "2026-01-24"}
  {"position": 97, "domain_name": "contentsquare.net", "date": "2026-01-24"}
  {"position": 98, "domain_name": "b-cdn.net", "date": "2026-01-24"}
  {"position": 99, "domain_name": "vtwenty.com", "date": "2026-01-24"}
  {"position": 100, "domain_name": "life360.com", "date": "2026-01-24"}
  {"position": 101, "domain_name": "alibaba.com", "date": "2026-01-24"}
  {"position": 102, "domain_name": "privacymanager.io", "date": "2026-01-24"}
  {"position": 103, "domain_name": "ubnt.com", "date": "2026-01-24"}
  {"position": 104, "domain_name": "zohoconference.com", "date": "2026-01-24"}
  {"position": 105, "domain_name": "ozon.ru", "date": "2026-01-24"}
  {"position": 106, "domain_name": "rutube.ru", "date": "2026-01-24"}
  {"position": 107, "domain_name": "pubmnet.com", "date": "2026-01-24"}
  {"position": 108, "domain_name": "tradplusad.com", "date": "2026-01-24"}
  {"position": 109, "domain_name": "queniuyk.com", "date": "2026-01-24"}
  {"position": 110, "domain_name": "tremorhub.com", "date": "2026-01-24"}
  {"position": 111, "domain_name": "aurasvc.io", "date": "2026-01-24"}
  {"position": 112, "domain_name": "goskope.com", "date": "2026-01-24"}
  {"position": 113, "domain_name": "fastly.net", "date": "2026-01-24"}
  {"position": 114, "domain_name": "cloud.microsoft", "date": "2026-01-24"}
  {"position": 115, "domain_name": "googletagservices.com", "date": "2026-01-24"}
  {"position": 116, "domain_name": "browser-intake-datadoghq.com", "date": "2026-01-24"}
  {"position": 117, "domain_name": "pluto.tv", "date": "2026-01-24"}
  {"position": 118, "domain_name": "tier1.it", "date": "2026-01-24"}
  {"position": 119, "domain_name": "alibabadns.com", "date": "2026-01-24"}
  {"position": 120, "domain_name": "yieldmo.com", "date": "2026-01-24"}
  {"position": 121, "domain_name": "cursor.sh", "date": "2026-01-24"}
  {"position": 122, "domain_name": "dns.google", "date": "2026-01-24"}
  {"position": 123, "domain_name": "aipx.co", "date": "2026-01-24"}
  {"position": 124, "domain_name": "telegram.me", "date": "2026-01-24"}
  {"position": 125, "domain_name": "ueiwsp.com", "date": "2026-01-24"}
  {"position": 126, "domain_name": "google.com.ni", "date": "2026-01-24"}
  {"position": 127, "domain_name": "qualtrics.com", "date": "2026-01-24"}
  {"position": 128, "domain_name": "myharmony.com", "date": "2026-01-24"}
  {"position": 129, "domain_name": "admanmedia.com", "date": "2026-01-24"}
  {"position": 130, "domain_name": "autonavi.com", "date": "2026-01-24"}
  {"position": 131, "domain_name": "unmsapp.com", "date": "2026-01-24"}
  {"position": 132, "domain_name": "baomoi.com", "date": "2026-01-24"}
  {"position": 133, "domain_name": "baidu.com", "date": "2026-01-24"}
  {"position": 134, "domain_name": "nordvpn.com", "date": "2026-01-24"}
  {"position": 135, "domain_name": "android.com", "date": "2026-01-24"}
  {"position": 136, "domain_name": "home-assistant.io", "date": "2026-01-24"}
  {"position": 137, "domain_name": "smilewanted.com", "date": "2026-01-24"}
  {"position": 138, "domain_name": "google.co.ma", "date": "2026-01-24"}
  {"position": 139, "domain_name": "google.dk", "date": "2026-01-24"}
  {"position": 140, "domain_name": "mysterium.network", "date": "2026-01-24"}
  {"position": 141, "domain_name": "mikrotik.com", "date": "2026-01-24"}
  {"position": 142, "domain_name": "mathtag.com", "date": "2026-01-24"}
  {"position": 143, "domain_name": "mozilla.org", "date": "2026-01-24"}
  {"position": 144, "domain_name": "outbrain.com", "date": "2026-01-24"}
  {"position": 145, "domain_name": "ttvnw.net", "date": "2026-01-24"}
  {"position": 146, "domain_name": "dino.ws", "date": "2026-01-24"}
  {"position": 147, "domain_name": "app-measurement.com", "date": "2026-01-24"}
  {"position": 148, "domain_name": "microsoft.us", "date": "2026-01-24"}
  {"position": 149, "domain_name": "shifen.com", "date": "2026-01-24"}
  {"position": 150, "domain_name": "avigilon.com", "date": "2026-01-24"}
  {"position": 151, "domain_name": "myfritz.net", "date": "2026-01-24"}
  {"position": 152, "domain_name": "criteo.com", "date": "2026-01-24"}
  {"position": 153, "domain_name": "quickconnect.to", "date": "2026-01-24"}
  {"position": 154, "domain_name": "google.com.fj", "date": "2026-01-24"}
  {"position": 155, "domain_name": "google.tk", "date": "2026-01-24"}
  {"position": 156, "domain_name": "connatix.com", "date": "2026-01-24"}
  {"position": 157, "domain_name": "ibm.com", "date": "2026-01-24"}
  {"position": 158, "domain_name": "bytedns1.com", "date": "2026-01-24"}
  {"position": 159, "domain_name": "bytefcdn-ttpeu.com", "date": "2026-01-24"}
  {"position": 160, "domain_name": "activeloop.online", "date": "2026-01-24"}
  {"position": 161, "domain_name": "alibabacloud.com", "date": "2026-01-24"}
  {"position": 162, "domain_name": "wfplv1yjgm.com", "date": "2026-01-24"}
  {"position": 163, "domain_name": "tesla.com", "date": "2026-01-24"}
  {"position": 164, "domain_name": "myss133.com", "date": "2026-01-24"}
  {"position": 165, "domain_name": "myseedbox.site", "date": "2026-01-24"}
  {"position": 166, "domain_name": "sinaimg.cn", "date": "2026-01-24"}
  {"position": 167, "domain_name": "skype.com", "date": "2026-01-24"}
  {"position": 168, "domain_name": "aeliax.com", "date": "2026-01-24"}
  {"position": 169, "domain_name": "sip.global", "date": "2026-01-24"}
  {"position": 170, "domain_name": "msidentity.com", "date": "2026-01-24"}
  {"position": 171, "domain_name": "live.net", "date": "2026-01-24"}
  {"position": 172, "domain_name": "aol.com", "date": "2026-01-24"}
  {"position": 173, "domain_name": "svc.ms", "date": "2026-01-24"}
  {"position": 174, "domain_name": "plex.tv", "date": "2026-01-24"}
  {"position": 175, "domain_name": "doubleverify.com", "date": "2026-01-24"}
  {"position": 176, "domain_name": "sat.gob.mx", "date": "2026-01-24"}
  {"position": 177, "domain_name": "figma.com", "date": "2026-01-24"}
  {"position": 178, "domain_name": "onenote.com", "date": "2026-01-24"}
  {"position": 179, "domain_name": "usgovcloudapi.net", "date": "2026-01-24"}
  {"position": 180, "domain_name": "icanhazip.com", "date": "2026-01-24"}
  {"position": 181, "domain_name": "one.one", "date": "2026-01-24"}
  {"position": 182, "domain_name": "roblox.com", "date": "2026-01-24"}
  {"position": 183, "domain_name": "dssott.com", "date": "2026-01-24"}
  {"position": 184, "domain_name": "alibabacorp.com", "date": "2026-01-24"}
  {"position": 185, "domain_name": "xnharfquw.com", "date": "2026-01-24"}
  {"position": 186, "domain_name": "hotmail.com", "date": "2026-01-24"}
  {"position": 187, "domain_name": "sonobi.com", "date": "2026-01-24"}
  {"position": 188, "domain_name": "mzstatic.com", "date": "2026-01-24"}
  {"position": 189, "domain_name": "gamepass.com", "date": "2026-01-24"}
  {"position": 190, "domain_name": "intuit.com", "date": "2026-01-24"}
  {"position": 191, "domain_name": "logicnow.us", "date": "2026-01-24"}
  {"position": 192, "domain_name": "pages.dev", "date": "2026-01-24"}
  {"position": 193, "domain_name": "fotmob.com", "date": "2026-01-24"}
  {"position": 194, "domain_name": "cookielaw.org", "date": "2026-01-24"}
  {"position": 195, "domain_name": "fwmrm.net", "date": "2026-01-24"}
  {"position": 196, "domain_name": "google-analytics.com", "date": "2026-01-24"}
  {"position": 197, "domain_name": "redditspace.com", "date": "2026-01-24"}
  {"position": 198, "domain_name": "cdn-apple.com", "date": "2026-01-24"}
  {"position": 199, "domain_name": "diseserver.net", "date": "2026-01-24"}
  {"position": 200, "domain_name": "discord.media", "date": "2026-01-24"}
  {"position": 201, "domain_name": "ikonkek2.com", "date": "2026-01-24"}
  {"position": 202, "domain_name": "uisp.com", "date": "2026-01-24"}
  {"position": 203, "domain_name": "indazn.com", "date": "2026-01-24"}
  {"position": 204, "domain_name": "samsungapps.com", "date": "2026-01-24"}
  {"position": 205, "domain_name": "google.sc", "date": "2026-01-24"}
  {"position": 206, "domain_name": "tubitv.com", "date": "2026-01-24"}
  {"position": 207, "domain_name": "rottor.dev", "date": "2026-01-24"}
  {"position": 208, "domain_name": "msecnd.net", "date": "2026-01-24"}
  {"position": 209, "domain_name": "cloudfunctions.net", "date": "2026-01-24"}
  {"position": 210, "domain_name": "cloudflareinsights.com", "date": "2026-01-24"}
  {"position": 211, "domain_name": "gotinder.com", "date": "2026-01-24"}
  {"position": 212, "domain_name": "cgm.com", "date": "2026-01-24"}
  {"position": 213, "domain_name": "cloudinary.com", "date": "2026-01-24"}
  {"position": 214, "domain_name": "adjust.com", "date": "2026-01-24"}
  {"position": 215, "domain_name": "infocyte.com", "date": "2026-01-24"}
  {"position": 216, "domain_name": "recaptcha.net", "date": "2026-01-24"}
  {"position": 217, "domain_name": "pstatic.net", "date": "2026-01-24"}
  {"position": 218, "domain_name": "rbxcdn.com", "date": "2026-01-24"}
  {"position": 219, "domain_name": "hdslb.com", "date": "2026-01-24"}
  {"position": 220, "domain_name": "ubi.com", "date": "2026-01-24"}
  {"position": 221, "domain_name": "weveryw.com", "date": "2026-01-24"}
  {"position": 222, "domain_name": "sophos.com", "date": "2026-01-24"}
  {"position": 223, "domain_name": "myqcloud.com", "date": "2026-01-24"}
  {"position": 224, "domain_name": "vivaldi.com", "date": "2026-01-24"}
  {"position": 225, "domain_name": "samsungosp.com", "date": "2026-01-24"}
  {"position": 226, "domain_name": "dual-s-msedge.net", "date": "2026-01-24"}
  {"position": 227, "domain_name": "datadoghq-browser-agent.com", "date": "2026-01-24"}
  {"position": 228, "domain_name": "shopify.com", "date": "2026-01-24"}
  {"position": 229, "domain_name": "gpubgm.com", "date": "2026-01-24"}
  {"position": 230, "domain_name": "perplexity.ai", "date": "2026-01-24"}
  {"position": 231, "domain_name": "seedtag.com", "date": "2026-01-24"}
  {"position": 232, "domain_name": "mp3tm.net", "date": "2026-01-24"}
  {"position": 233, "domain_name": "yieldlab.net", "date": "2026-01-24"}
  {"position": 234, "domain_name": "awsglobalaccelerator.com", "date": "2026-01-24"}
  {"position": 235, "domain_name": "nr-data.net", "date": "2026-01-24"}
  {"position": 236, "domain_name": "bfjwl.com", "date": "2026-01-24"}
  {"position": 237, "domain_name": "ureca-lab.com", "date": "2026-01-24"}
  {"position": 238, "domain_name": "ya.ru", "date": "2026-01-24"}
  {"position": 239, "domain_name": "teads.tv", "date": "2026-01-24"}
  {"position": 240, "domain_name": "ruijienetworks.com", "date": "2026-01-24"}
  {"position": 241, "domain_name": "adobe.io", "date": "2026-01-24"}
  {"position": 242, "domain_name": "dnsv1.com.cn", "date": "2026-01-24"}
  {"position": 243, "domain_name": "seagate.com", "date": "2026-01-24"}
  {"position": 244, "domain_name": "lgtviot.com", "date": "2026-01-24"}
  {"position": 245, "domain_name": "mossru.com", "date": "2026-01-24"}
  {"position": 246, "domain_name": "mmstat.com", "date": "2026-01-24"}
  {"position": 247, "domain_name": "volcgslb.com", "date": "2026-01-24"}
  {"position": 248, "domain_name": "roku.com", "date": "2026-01-24"}
  {"position": 249, "domain_name": "bpcyber.com", "date": "2026-01-24"}
  {"position": 250, "domain_name": "cowmanager.com", "date": "2026-01-24"}
  {"position": 251, "domain_name": "dyndns.org", "date": "2026-01-24"}
  {"position": 252, "domain_name": "bilibili.com", "date": "2026-01-24"}
  {"position": 253, "domain_name": "tado.com", "date": "2026-01-24"}
  {"position": 254, "domain_name": "growatt.com", "date": "2026-01-24"}
  {"position": 255, "domain_name": "enphaseenergy.com", "date": "2026-01-24"}
  {"position": 256, "domain_name": "walgreens.com", "date": "2026-01-24"}
  {"position": 257, "domain_name": "dishanywhere.com", "date": "2026-01-24"}
  {"position": 258, "domain_name": "mediatek.com", "date": "2026-01-24"}
  {"position": 259, "domain_name": "justbuyitinc.com", "date": "2026-01-24"}
  {"position": 260, "domain_name": "hubcloud.com.cn", "date": "2026-01-24"}
  {"position": 261, "domain_name": "tdnsv6.com", "date": "2026-01-24"}
  {"position": 262, "domain_name": "2mdn.net", "date": "2026-01-24"}
  {"position": 263, "domain_name": "doordash.com", "date": "2026-01-24"}
  {"position": 264, "domain_name": "netflix.net", "date": "2026-01-24"}
  {"position": 265, "domain_name": "swiftkey.com", "date": "2026-01-24"}
  {"position": 266, "domain_name": "dnsperf.com", "date": "2026-01-24"}
  {"position": 267, "domain_name": "acobt.tech", "date": "2026-01-24"}
  {"position": 268, "domain_name": "junese.de", "date": "2026-01-24"}
  {"position": 269, "domain_name": "xhamster.com", "date": "2026-01-24"}
  {"position": 270, "domain_name": "real-debrid.com", "date": "2026-01-24"}
  {"position": 271, "domain_name": "pddpic.com", "date": "2026-01-24"}
  {"position": 272, "domain_name": "google.la", "date": "2026-01-24"}
  {"position": 273, "domain_name": "arcgis.com", "date": "2026-01-24"}
  {"position": 274, "domain_name": "pf-d.ca", "date": "2026-01-24"}
  {"position": 275, "domain_name": "workers.dev", "date": "2026-01-24"}
  {"position": 276, "domain_name": "tejaswisingh.com", "date": "2026-01-24"}
  {"position": 277, "domain_name": "cootlogix.com", "date": "2026-01-24"}
  {"position": 278, "domain_name": "iponweb.net", "date": "2026-01-24"}
  {"position": 279, "domain_name": "maio.jp", "date": "2026-01-24"}
  {"position": 280, "domain_name": "inmobicdn.net", "date": "2026-01-24"}
  {"position": 281, "domain_name": "firefox.com", "date": "2026-01-24"}
  {"position": 282, "domain_name": "mysunlife.ca", "date": "2026-01-24"}
  {"position": 283, "domain_name": "avcdn.net", "date": "2026-01-24"}
  {"position": 284, "domain_name": "avast.com", "date": "2026-01-24"}
  {"position": 285, "domain_name": "mediation.goog", "date": "2026-01-24"}
  {"position": 286, "domain_name": "xvideos-cdn.com", "date": "2026-01-24"}
  {"position": 287, "domain_name": "fortinet.net", "date": "2026-01-24"}
  {"position": 288, "domain_name": "chartbeat.net", "date": "2026-01-24"}
  {"position": 289, "domain_name": "cdn-kaspi.kz", "date": "2026-01-24"}
  {"position": 290, "domain_name": "gather-ai.com", "date": "2026-01-24"}
  {"position": 291, "domain_name": "listdl.com", "date": "2026-01-24"}
  {"position": 292, "domain_name": "redditmedia.com", "date": "2026-01-24"}
  {"position": 293, "domain_name": "google.com.br", "date": "2026-01-24"}
  {"position": 294, "domain_name": "unicacdn.app", "date": "2026-01-24"}
  {"position": 295, "domain_name": "adobess.com", "date": "2026-01-24"}
  {"position": 296, "domain_name": "qrzhumfdx.com", "date": "2026-01-24"}
  {"position": 297, "domain_name": "ouraring.com", "date": "2026-01-24"}
  {"position": 298, "domain_name": "uimz80fgj.com", "date": "2026-01-24"}
  {"position": 299, "domain_name": "serverbid.com", "date": "2026-01-24"}
  {"position": 300, "domain_name": "sway-extensions.com", "date": "2026-01-24"}
  {"position": 301, "domain_name": "new-line.net", "date": "2026-01-24"}
  {"position": 302, "domain_name": "mnaspm.com", "date": "2026-01-24"}
  {"position": 303, "domain_name": "xiaohongshu.com", "date": "2026-01-24"}
  {"position": 304, "domain_name": "singular.net", "date": "2026-01-24"}
  {"position": 305, "domain_name": "google.mg", "date": "2026-01-24"}
  {"position": 306, "domain_name": "remotepc.com", "date": "2026-01-24"}
  {"position": 307, "domain_name": "datadome.co", "date": "2026-01-24"}
  {"position": 308, "domain_name": "201.in-addr.arpa", "date": "2026-01-24"}
  {"position": 309, "domain_name": "samokat.ru", "date": "2026-01-24"}
  {"position": 310, "domain_name": "edgekey.net", "date": "2026-01-24"}
  {"position": 311, "domain_name": "amazon.nl", "date": "2026-01-24"}
  {"position": 312, "domain_name": "argotunnel.com", "date": "2026-01-24"}
  {"position": 313, "domain_name": "redditstatic.com", "date": "2026-01-24"}
  {"position": 314, "domain_name": "twibida.com", "date": "2026-01-24"}
  {"position": 315, "domain_name": "hiwifi.com", "date": "2026-01-24"}
  {"position": 316, "domain_name": "demounit.net", "date": "2026-01-24"}
  {"position": 317, "domain_name": "accompany.com", "date": "2026-01-24"}
  {"position": 318, "domain_name": "atlassian.com", "date": "2026-01-24"}
  {"position": 319, "domain_name": "dnsgermany1.com", "date": "2026-01-24"}
  {"position": 320, "domain_name": "in2-consulting.fr", "date": "2026-01-24"}
  {"position": 321, "domain_name": "eurosport.com", "date": "2026-01-24"}
  {"position": 322, "domain_name": "urbantz.com", "date": "2026-01-24"}
  {"position": 323, "domain_name": "google.tl", "date": "2026-01-24"}
  {"position": 324, "domain_name": "google.com.bn", "date": "2026-01-24"}
  {"position": 325, "domain_name": "herokudns.com", "date": "2026-01-24"}
  {"position": 326, "domain_name": "pbstck.com", "date": "2026-01-24"}
  {"position": 327, "domain_name": "vimeo.com", "date": "2026-01-24"}
  {"position": 328, "domain_name": "google.com.do", "date": "2026-01-24"}
  {"position": 329, "domain_name": "qnips.com", "date": "2026-01-24"}
  {"position": 330, "domain_name": "entrust.net", "date": "2026-01-24"}
  {"position": 331, "domain_name": "4dvertible.com", "date": "2026-01-24"}
  {"position": 332, "domain_name": "sendbird.com", "date": "2026-01-24"}
  {"position": 333, "domain_name": "lgtvcommon.com", "date": "2026-01-24"}
  {"position": 334, "domain_name": "tiny-vps.com", "date": "2026-01-24"}
  {"position": 335, "domain_name": "twitter.com", "date": "2026-01-24"}
  {"position": 336, "domain_name": "18.in-addr.arpa", "date": "2026-01-24"}
  {"position": 337, "domain_name": "i18n-pglstatp.com", "date": "2026-01-24"}
  {"position": 338, "domain_name": "purestorage.com", "date": "2026-01-24"}
  {"position": 339, "domain_name": "disney-plus.net", "date": "2026-01-24"}
  {"position": 340, "domain_name": "siriusxm.com", "date": "2026-01-24"}
  {"position": 341, "domain_name": "google.st", "date": "2026-01-24"}
  {"position": 342, "domain_name": "steamstatic.com", "date": "2026-01-24"}
  {"position": 343, "domain_name": "newtrack.info", "date": "2026-01-24"}
  {"position": 344, "domain_name": "auerproxy.de", "date": "2026-01-24"}
  {"position": 345, "domain_name": "bitwarden.com", "date": "2026-01-24"}
  {"position": 346, "domain_name": "google.cf", "date": "2026-01-24"}
  {"position": 347, "domain_name": "public-trust.com", "date": "2026-01-24"}
  {"position": 348, "domain_name": "privacysandboxservices.com", "date": "2026-01-24"}
  {"position": 349, "domain_name": "google.iq", "date": "2026-01-24"}
  {"position": 350, "domain_name": "adguard-vpn.online", "date": "2026-01-24"}
  {"position": 351, "domain_name": "rsecorp.com", "date": "2026-01-24"}
  {"position": 352, "domain_name": "tradingview.com", "date": "2026-01-24"}
  {"position": 353, "domain_name": "spotifycdn.com", "date": "2026-01-24"}
  {"position": 354, "domain_name": "att.com", "date": "2026-01-24"}
  {"position": 355, "domain_name": "sparteo.com", "date": "2026-01-24"}
  {"position": 356, "domain_name": "pcvisit.de", "date": "2026-01-24"}
  {"position": 357, "domain_name": "cloud.com", "date": "2026-01-24"}
  {"position": 358, "domain_name": "samotennis.com", "date": "2026-01-24"}
  {"position": 359, "domain_name": "alibaba-inc.com", "date": "2026-01-24"}
  {"position": 360, "domain_name": "powerapps.com", "date": "2026-01-24"}
  {"position": 361, "domain_name": "appier.net", "date": "2026-01-24"}
  {"position": 362, "domain_name": "exp-tas.com", "date": "2026-01-24"}
  {"position": 363, "domain_name": "samsungelectronics.com", "date": "2026-01-24"}
  {"position": 364, "domain_name": "nila.design", "date": "2026-01-24"}
  {"position": 365, "domain_name": "zenlayer.net", "date": "2026-01-24"}
  {"position": 366, "domain_name": "kookjar.com", "date": "2026-01-24"}
  {"position": 367, "domain_name": "meta.com", "date": "2026-01-24"}
  {"position": 368, "domain_name": "axissecurity.com", "date": "2026-01-24"}
  {"position": 369, "domain_name": "pmbmonetize.live", "date": "2026-01-24"}
  {"position": 370, "domain_name": "robin-flow.com", "date": "2026-01-24"}
  {"position": 371, "domain_name": "traffmonetizer.com", "date": "2026-01-24"}
  {"position": 372, "domain_name": "coralogix.com", "date": "2026-01-24"}
  {"position": 373, "domain_name": "114.in-addr.arpa", "date": "2026-01-24"}
  {"position": 374, "domain_name": "arin.net", "date": "2026-01-24"}
  {"position": 375, "domain_name": "liongard.com", "date": "2026-01-24"}
  {"position": 376, "domain_name": "t-mobile.com", "date": "2026-01-24"}
  {"position": 377, "domain_name": "adobe.net", "date": "2026-01-24"}
  {"position": 378, "domain_name": "hlb.com.my", "date": "2026-01-24"}
  {"position": 379, "domain_name": "104.in-addr.arpa", "date": "2026-01-24"}
  {"position": 380, "domain_name": "picarto.tv", "date": "2026-01-24"}
  {"position": 381, "domain_name": "lgsmartad.com", "date": "2026-01-24"}
  {"position": 382, "domain_name": "cdnhwc2.com", "date": "2026-01-24"}
  {"position": 383, "domain_name": "fastly-masque.net", "date": "2026-01-24"}
  {"position": 384, "domain_name": "adobeprimetime.com", "date": "2026-01-24"}
  {"position": 385, "domain_name": "opera.com", "date": "2026-01-24"}
  {"position": 386, "domain_name": "hochiminhcity.gov.vn", "date": "2026-01-24"}
  {"position": 387, "domain_name": "muxado.net", "date": "2026-01-24"}
  {"position": 388, "domain_name": "queniuwx.com", "date": "2026-01-24"}
  {"position": 389, "domain_name": "telephony.goog", "date": "2026-01-24"}
  {"position": 390, "domain_name": "network-auth.com", "date": "2026-01-24"}
  {"position": 391, "domain_name": "google.com.mm", "date": "2026-01-24"}
  {"position": 392, "domain_name": "grafana.com", "date": "2026-01-24"}
  {"position": 393, "domain_name": "servidor101.xyz", "date": "2026-01-24"}
  {"position": 394, "domain_name": "google.co.ck", "date": "2026-01-24"}
  {"position": 395, "domain_name": "usenetbucket.com", "date": "2026-01-24"}
  {"position": 396, "domain_name": "142.in-addr.arpa", "date": "2026-01-24"}
  {"position": 397, "domain_name": "getgrass.io", "date": "2026-01-24"}
  {"position": 398, "domain_name": "aliexpress.com", "date": "2026-01-24"}
  {"position": 399, "domain_name": "linksys.com", "date": "2026-01-24"}
  {"position": 400, "domain_name": "journeymv.com", "date": "2026-01-24"}
  {"position": 401, "domain_name": "liveperson.net", "date": "2026-01-24"}
  {"position": 402, "domain_name": "imrworldwide.com", "date": "2026-01-24"}
  {"position": 403, "domain_name": "google.nl", "date": "2026-01-24"}
  {"position": 404, "domain_name": "waconazure.com", "date": "2026-01-24"}
  {"position": 405, "domain_name": "rtbhouse.com", "date": "2026-01-24"}
  {"position": 406, "domain_name": "rimon.net.il", "date": "2026-01-24"}
  {"position": 407, "domain_name": "linkplay.com", "date": "2026-01-24"}
  {"position": 408, "domain_name": "kbprycjim.com", "date": "2026-01-24"}
  {"position": 409, "domain_name": "64.in-addr.arpa", "date": "2026-01-24"}
  {"position": 410, "domain_name": "adsrvr.org", "date": "2026-01-24"}
  {"position": 411, "domain_name": "salesmartly.com", "date": "2026-01-24"}
  {"position": 412, "domain_name": "fieldmuseum.tech", "date": "2026-01-24"}
  {"position": 413, "domain_name": "ppmxfa.com", "date": "2026-01-24"}
  {"position": 414, "domain_name": "188.in-addr.arpa", "date": "2026-01-24"}
  {"position": 415, "domain_name": "cian.ru", "date": "2026-01-24"}
  {"position": 416, "domain_name": "167.in-addr.arpa", "date": "2026-01-24"}
  {"position": 417, "domain_name": "erome.com", "date": "2026-01-24"}
  {"position": 418, "domain_name": "google.co.kr", "date": "2026-01-24"}
  {"position": 419, "domain_name": "ststandard.com", "date": "2026-01-24"}
  {"position": 420, "domain_name": "mintivo.co.uk", "date": "2026-01-24"}
  {"position": 421, "domain_name": "markul.net", "date": "2026-01-24"}
  {"position": 422, "domain_name": "yabyqd.com", "date": "2026-01-24"}
  {"position": 423, "domain_name": "doppiocdn.com", "date": "2026-01-24"}
  {"position": 424, "domain_name": "cdnhwcoem01.com", "date": "2026-01-24"}
  {"position": 425, "domain_name": "wechatpay.cn", "date": "2026-01-24"}
  {"position": 426, "domain_name": "claas.com", "date": "2026-01-24"}
  {"position": 427, "domain_name": "insightexpressai.com", "date": "2026-01-24"}
  {"position": 428, "domain_name": "chartbeat.com", "date": "2026-01-24"}
  {"position": 429, "domain_name": "a-mx.net", "date": "2026-01-24"}
  {"position": 430, "domain_name": "playsimple.games", "date": "2026-01-24"}
  {"position": 431, "domain_name": "huawei.com", "date": "2026-01-24"}
  {"position": 432, "domain_name": "google.cm", "date": "2026-01-24"}
  {"position": 433, "domain_name": "urbanairship.com", "date": "2026-01-24"}
  {"position": 434, "domain_name": "youdao.com", "date": "2026-01-24"}
  {"position": 435, "domain_name": "shopifycdn.com", "date": "2026-01-24"}
  {"position": 436, "domain_name": "ea.com", "date": "2026-01-24"}
  {"position": 437, "domain_name": "telegram.org", "date": "2026-01-24"}
  {"position": 438, "domain_name": "ajcloud.net", "date": "2026-01-24"}
  {"position": 439, "domain_name": "cambiumnetworks.com", "date": "2026-01-24"}
  {"position": 440, "domain_name": "service-now.com", "date": "2026-01-24"}
  {"position": 441, "domain_name": "rackcdn.com", "date": "2026-01-24"}
  {"position": 442, "domain_name": "vasdgame.com", "date": "2026-01-24"}
  {"position": 443, "domain_name": "fastclick.net", "date": "2026-01-24"}
  {"position": 444, "domain_name": "codebreaker.hr", "date": "2026-01-24"}
  {"position": 445, "domain_name": "google.bt", "date": "2026-01-24"}
  {"position": 446, "domain_name": "mndx1.com", "date": "2026-01-24"}
  {"position": 447, "domain_name": "rings.solutions", "date": "2026-01-24"}
  {"position": 448, "domain_name": "dbn.de", "date": "2026-01-24"}
  {"position": 449, "domain_name": "n0xkq4ka321.com", "date": "2026-01-24"}
  {"position": 450, "domain_name": "bypassgod218.com", "date": "2026-01-24"}
  {"position": 451, "domain_name": "google.bi", "date": "2026-01-24"}
  {"position": 452, "domain_name": "sectigo.com", "date": "2026-01-24"}
  {"position": 453, "domain_name": "faz.net", "date": "2026-01-24"}
  {"position": 454, "domain_name": "egt-ong.com", "date": "2026-01-24"}
  {"position": 455, "domain_name": "intercom.com", "date": "2026-01-24"}
  {"position": 456, "domain_name": "fidelity.com", "date": "2026-01-24"}
  {"position": 457, "domain_name": "aliyuncsslbintl.com", "date": "2026-01-24"}
  {"position": 458, "domain_name": "vk.com", "date": "2026-01-24"}
  {"position": 459, "domain_name": "mailgun.org", "date": "2026-01-24"}
  {"position": 460, "domain_name": "columbus2024.com", "date": "2026-01-24"}
  {"position": 461, "domain_name": "l-agent.me", "date": "2026-01-24"}
  {"position": 462, "domain_name": "fbsbx.com", "date": "2026-01-24"}
  {"position": 463, "domain_name": "abacco.com", "date": "2026-01-24"}
  {"position": 464, "domain_name": "youversionapi.com", "date": "2026-01-24"}
  {"position": 465, "domain_name": "plex.direct", "date": "2026-01-24"}
  {"position": 466, "domain_name": "cleverq.de", "date": "2026-01-24"}
  {"position": 467, "domain_name": "steampowered.com", "date": "2026-01-24"}
  {"position": 468, "domain_name": "medallia.com", "date": "2026-01-24"}
  {"position": 469, "domain_name": "agora.io", "date": "2026-01-24"}
  {"position": 470, "domain_name": "msauthimages.net", "date": "2026-01-24"}
  {"position": 471, "domain_name": "pointclickcare.com", "date": "2026-01-24"}
  {"position": 472, "domain_name": "amazon.com", "date": "2026-01-24"}
  {"position": 473, "domain_name": "s-onetag.com", "date": "2026-01-24"}
  {"position": 474, "domain_name": "google.com.my", "date": "2026-01-24"}
  {"position": 475, "domain_name": "cia158.net", "date": "2026-01-24"}
  {"position": 476, "domain_name": "prreqcroab.icu", "date": "2026-01-24"}
  {"position": 477, "domain_name": "startappservice.com", "date": "2026-01-24"}
  {"position": 478, "domain_name": "trustpilot.com", "date": "2026-01-24"}
  {"position": 479, "domain_name": "igodigital.com", "date": "2026-01-24"}
  {"position": 480, "domain_name": "google.gm", "date": "2026-01-24"}
  {"position": 481, "domain_name": "windows.net", "date": "2026-01-24"}
  {"position": 482, "domain_name": "open-meteo.com", "date": "2026-01-24"}
  {"position": 483, "domain_name": "jpush.io", "date": "2026-01-24"}
  {"position": 484, "domain_name": "cfdata.org", "date": "2026-01-24"}
  {"position": 485, "domain_name": "wscvip.cn", "date": "2026-01-24"}
  {"position": 486, "domain_name": "gamedistribution.com", "date": "2026-01-24"}
  {"position": 487, "domain_name": "wix.com", "date": "2026-01-24"}
  {"position": 488, "domain_name": "detailroi.com", "date": "2026-01-24"}
  {"position": 489, "domain_name": "vedcdnlb.com", "date": "2026-01-24"}
  {"position": 490, "domain_name": "usertrust.com", "date": "2026-01-24"}
  {"position": 491, "domain_name": "izatcloud.net", "date": "2026-01-24"}
  {"position": 492, "domain_name": "amagi.tv", "date": "2026-01-24"}
  {"position": 493, "domain_name": "google.com.pk", "date": "2026-01-24"}
  {"position": 494, "domain_name": "neshanmap.ir", "date": "2026-01-24"}
  {"position": 495, "domain_name": "finsky.cyou", "date": "2026-01-24"}
  {"position": 496, "domain_name": "azurecontainerapps.io", "date": "2026-01-24"}
  {"position": 497, "domain_name": "xnxx-cdn.com", "date": "2026-01-24"}
  {"position": 498, "domain_name": "vitrinabeat.ru", "date": "2026-01-24"}
  {"position": 499, "domain_name": "pgoriginad.com", "date": "2026-01-24"}
  {"position": 500, "domain_name": "google.co.ug", "date": "2026-01-24"}
